Metadata-Version: 1.1
Name: djangocms-ga-optout
Version: 0.0.1
Summary: A djangoCMS Plugin that creates an Opt-Out link for Google Analytics.
Home-page: https://github.com/Blueshoe/djangocms-ga-optout
Author: Maximilian Muth
Author-email: max@blueshoe.de
License: MIT License
